{
  "name": "High Councillor's Robe",
  "quality": "Uncommon",
  "icon": "inv_chest_cloth_12",
  "tooltip": "<table><tr><td><!--nstart--><b class=\"q2\">High Councillor's Robe</b><!--nend--><!--ndstart--><!--ndend--><span class=\"q\"><br>Item Level <!--ilvl-->64</span><!--bo--><br />Binds when equipped<table width=\"100%\"><tr><td>Chest</td><th><!--scstart4:1--><span class=\"q1\">Cloth</span><!--scend--></th></tr></table><span><!--amr-->82 Armor</span><br><!--re--><span class=\"q2\">&lt;Random enchantment&gt;</span><!--ebstats--><!--egstats--><!--eistats--><!--e--><!--ps--><br>Durability 70 / 70</td></tr></table><table><tr><td>Requires Level <!--rlvl-->59<!--itemEffects:1--><div class=\"whtt-sellprice\">Sell Price: <span class=\"moneygold\">1</span> <span class=\"moneysilver\">97</span> <span class=\"moneycopper\">72</span></div></td></tr></table>",
  "url": "/item=10143/high-councillors-robe",
  "image": "https://wow.zamimg.com/images/wow/icons/medium/inv_chest_cloth_12.jpg",
  "id": "10143",
  "slug": "high-councillors-robe"
}