{
  "name": "Graverot Cape",
  "quality": "Rare",
  "icon": "inv_misc_cape_19",
  "tooltip": "<table><tr><td><!--nstart--><b class=\"q3\">Graverot Cape</b><!--nend--><!--ndstart--><!--ndend--><span class=\"q\"><br>Item Level <!--ilvl-->55</span><!--bo--><br />Binds when picked up<table width=\"100%\"><tr><td>Back</td></table><span><!--amr-->39 Armor</span><br><span><!--stat7-->+15 Stamina</span><br><span><!--stat6-->+6 Spirit</span><!--ebstats--><!--egstats--><!--eistats--><!--e--><!--ps--></td></tr></table><table><tr><td>Requires Level <!--rlvl-->50<!--itemEffects:1--><div class=\"whtt-sellprice\">Sell Price: <span class=\"moneygold\">1</span> <span class=\"moneysilver\">16</span> <span class=\"moneycopper\">55</span></div><div class=\"whtt-extra whtt-droppedby\">Dropped by: Anub'shiah</div><div class=\"whtt-extra whtt-dropchance\">Drop Chance: 30.62%</div></td></tr></table>",
  "url": "/item=11677/graverot-cape",
  "image": "https://wow.zamimg.com/images/wow/icons/medium/inv_misc_cape_19.jpg",
  "id": "11677",
  "slug": "graverot-cape"
}