{
  "name": "Mugthol's Helm",
  "quality": "Rare",
  "icon": "inv_helmet_25",
  "tooltip": "<table><tr><td><!--nstart--><b class=\"q3\">Mugthol's Helm</b><!--nend--><!--ndstart--><!--ndend--><span class=\"q\"><br>Item Level <!--ilvl-->52</span><!--bo--><br />Binds when equipped<table width=\"100%\"><tr><td>Head</td><th><!--scstart4:4--><span class=\"q1\">Plate</span><!--scend--></th></tr></table><span><!--amr-->445 Armor</span><br><span><!--stat4-->+10 Strength</span><br><span><!--stat7-->+17 Stamina</span><br><span><!--stat6-->+17 Spirit</span><!--ebstats--><!--egstats--><!--eistats--><!--e--><!--ps--><br>Durability 80 / 80</td></tr></table><table><tr><td>Requires Level <!--rlvl-->47<!--itemEffects:1--><div class=\"whtt-sellprice\">Sell Price: <span class=\"moneysilver\">90</span> <span class=\"moneycopper\">80</span></div></td></tr></table>",
  "url": "/item=13073/mugthols-helm",
  "image": "https://wow.zamimg.com/images/wow/icons/medium/inv_helmet_25.jpg",
  "id": "13073",
  "slug": "mugthols-helm"
}