{
  "name": "Buccaneer's Cord",
  "quality": "Uncommon",
  "icon": "inv_belt_22",
  "tooltip": "<table><tr><td><!--nstart--><b class=\"q2\">Buccaneer's Cord</b><!--nend--><!--ndstart--><!--ndend--><span class=\"q\"><br>Item Level <!--ilvl-->20</span><!--bo--><br />Binds when equipped<table width=\"100%\"><tr><td>Waist</td><th><!--scstart4:1--><span class=\"q1\">Cloth</span><!--scend--></th></tr></table><span><!--amr-->19 Armor</span><br><!--re--><span class=\"q2\">&lt;Random enchantment&gt;</span><!--ebstats--><!--egstats--><!--eistats--><!--e--><!--ps--><br>Durability 20 / 20</td></tr></table><table><tr><td>Requires Level <!--rlvl-->15<!--itemEffects:1--><div class=\"whtt-sellprice\">Sell Price: <span class=\"moneysilver\">2</span> <span class=\"moneycopper\">81</span></div></td></tr></table>",
  "url": "/item=14173/buccaneers-cord",
  "image": "https://wow.zamimg.com/images/wow/icons/medium/inv_belt_22.jpg",
  "id": "14173",
  "slug": "buccaneers-cord"
}