{
  "name": "Heroic Armor",
  "quality": "Uncommon",
  "icon": "inv_chest_chain_10",
  "tooltip": "<table><tr><td><!--nstart--><b class=\"q2\">Heroic Armor</b><!--nend--><!--ndstart--><!--ndend--><span class=\"q\"><br>Item Level <!--ilvl-->62</span><!--bo--><br />Binds when equipped<table width=\"100%\"><tr><td>Chest</td><th><!--scstart4:4--><span class=\"q1\">Plate</span><!--scend--></th></tr></table><span><!--amr-->588 Armor</span><br><!--re--><span class=\"q2\">&lt;Random enchantment&gt;</span><!--ebstats--><!--egstats--><!--eistats--><!--e--><!--ps--><br>Durability 115 / 115</td></tr></table><table><tr><td>Requires Level <!--rlvl-->57<!--itemEffects:1--><div class=\"whtt-sellprice\">Sell Price: <span class=\"moneygold\">1</span> <span class=\"moneysilver\">85</span> <span class=\"moneycopper\">48</span></div></td></tr></table>",
  "url": "/item=14931/heroic-armor",
  "image": "https://wow.zamimg.com/images/wow/icons/medium/inv_chest_chain_10.jpg",
  "id": "14931",
  "slug": "heroic-armor"
}