{
  "name": "Marauder's Tunic",
  "quality": "Uncommon",
  "icon": "inv_chest_plate04",
  "tooltip": "<table><tr><td><!--nstart--><b class=\"q2\">Marauder's Tunic</b><!--nend--><!--ndstart--><!--ndend--><span class=\"q\"><br>Item Level <!--ilvl-->40</span><!--bo--><br />Binds when equipped<table width=\"100%\"><tr><td>Chest</td><th><!--scstart4:3--><span class=\"q1\">Mail</span><!--scend--></th></tr></table><span><!--amr-->231 Armor</span><br><!--re--><span class=\"q2\">&lt;Random enchantment&gt;</span><!--ebstats--><!--egstats--><!--eistats--><!--e--><!--ps--><br>Durability 100 / 100</td></tr></table><table><tr><td>Requires Level <!--rlvl-->35<!--itemEffects:1--><div class=\"whtt-sellprice\">Sell Price: <span class=\"moneysilver\">66</span> <span class=\"moneycopper\">66</span></div></td></tr></table>",
  "url": "/item=15567/marauders-tunic",
  "image": "https://wow.zamimg.com/images/wow/icons/medium/inv_chest_plate04.jpg",
  "id": "15567",
  "slug": "marauders-tunic"
}