{
  "name": "General's Chain Wristguards",
  "quality": "Epic",
  "icon": "inv_bracer_16",
  "tooltip": "<table><tr><td><!--nstart--><b class=\"q4\">General's Chain Wristguards</b><!--nend--><!--ndstart--><!--ndend--><span class=\"q\"><br>Item Level <!--ilvl-->65</span><!--bo--><br />Binds when picked up<br />Unique<table width=\"100%\"><tr><td>Wrist</td><th><!--scstart4:3--><span class=\"q1\">Mail</span><!--scend--></th></tr></table><span><!--amr-->182 Armor</span><br><span><!--stat3-->+20 Agility</span><br><span><!--stat5-->+7 Intellect</span><br><span><!--stat7-->+10 Stamina</span><!--ebstats--><!--egstats--><!--eistats--><!--e--><!--ps--><br>Durability 50 / 50<div class=\"wowhead-tooltip-item-classes\">Classes: <a href=\"/class=3\" class=\"c3\">Hunter</a></div></td></tr></table><table><tr><td>Requires Level <!--rlvl-->60<br>Requires <span class=\"icon-horde\">General</span> <span class=\"icon-alliance\">Marshal</span><!--itemEffects:1--><div class=\"whtt-sellprice\">Sell Price: <span class=\"moneygold\">1</span> <span class=\"moneysilver\">30</span> <span class=\"moneycopper\">73</span></div></td></tr></table>",
  "url": "/item=16570/generals-chain-wristguards",
  "image": "https://wow.zamimg.com/images/wow/icons/medium/inv_bracer_16.jpg",
  "id": "16570",
  "slug": "generals-chain-wristguards"
}