{
  "name": "Sword of Decay",
  "quality": "Rare",
  "icon": "inv_sword_26",
  "tooltip": "<table><tr><td><!--nstart--><b class=\"q3\">Sword of Decay</b><!--nend--><!--ndstart--><!--ndend--><span class=\"q\"><br>Item Level <!--ilvl-->28</span><!--bo--><br />Binds when equipped<table width=\"100%\"><tr><td>Main Hand</td><th><!--scstart2:7--><span class=\"q1\">Sword</span><!--scend--></th></tr></table><table width=\"100%\"><tr>\n    <td><span><!--dmg-->33 - 62 Damage</span></td>\n    <th>Speed <!--spd-->2.70</th>\n</tr></table><!--dps-->(17.59 damage per second)<!--ebstats--><!--egstats--><!--eistats--><!--e--><!--ps--><br>Durability 80 / 80</td></tr></table><table><tr><td>Requires Level <!--rlvl-->23<br><span class=\"q2\">Chance on hit: <a href=\"/spell=13528\" class=\"q2\">Reduces target's Strength by 10 for 30 sec.</a></span><!--itemEffects:1--><div class=\"whtt-sellprice\">Sell Price: <span class=\"moneysilver\">45</span> <span class=\"moneycopper\">62</span></div></td></tr></table>",
  "url": "/item=1727/sword-of-decay",
  "image": "https://wow.zamimg.com/images/wow/icons/medium/inv_sword_26.jpg",
  "id": "1727",
  "slug": "sword-of-decay"
}