{
  "name": "QAEnchant Weapon Healing Power",
  "quality": "Common",
  "icon": "inv_jewelry_talisman_01",
  "tooltip": "<table><tr><td><!--nstart--><b class=\"q1\">QAEnchant Weapon Healing Power</b><!--nend--><!--ndstart--><!--ndend--><span class=\"q whtt-extra whtt-ilvl\"><br>Item Level <!--ilvl-->1</span><!--bo--><!--ebstats--><!--egstats--><!--eistats--></td></tr></table><table><tr><td><span class=\"q2\">Use: <a href=\"/spell=23144\" class=\"q2\">Permanently enchant a Melee Weapon to add up to 55 points of healing to healing spells.</a></span></td></tr></table>",
  "url": "/item=18669/qaenchant-weapon-healing-power",
  "image": "https://wow.zamimg.com/images/wow/icons/medium/inv_jewelry_talisman_01.jpg",
  "id": "18669",
  "slug": "qaenchant-weapon-healing-power"
}