{
  "name": "Formula: Enchant Weapon - Mighty Intellect",
  "quality": "Common",
  "icon": "inv_misc_note_01",
  "tooltip": "<table><tr><td><!--nstart--><b class=\"q1\">Formula: Enchant Weapon - Mighty Intellect</b><!--nend--><!--ndstart--><!--ndend--><span class=\"q whtt-extra whtt-ilvl\"><br>Item Level <!--ilvl-->70</span><!--bo--><br />Binds when picked up<!--ebstats--><!--egstats--><!--eistats--></td></tr></table><table><tr><td>Requires <a href=\"/skill=333\" class=\"q1\">Enchanting</a> (300)<br><span class=\"q2\">Use: <a href=\"/spell=23810\" class=\"q2\">Teaches you how to permanently enchant a weapon to increase your intellect by 22.</a></span><div class=\"whtt-sellprice\">Sell Price: <span class=\"moneygold\">2</span> <span class=\"moneysilver\">50</span></div></td></tr></table>",
  "completion_category": "9",
  "url": "/item=19449/formula-enchant-weapon-mighty-intellect",
  "image": "https://wow.zamimg.com/images/wow/icons/medium/inv_misc_note_01.jpg",
  "id": "19449",
  "slug": "formula-enchant-weapon-mighty-intellect"
}