{
  "name": "Syncretist's Sigil",
  "quality": "Rare",
  "icon": "spell_holy_prayerofhealing",
  "tooltip": "<table><tr><td><!--nstart--><b class=\"q3\">Syncretist's Sigil</b><!--nend--><!--ndstart--><!--ndend--><span class=\"q whtt-extra whtt-ilvl\"><br>Item Level <!--ilvl-->60</span><!--bo--><br />Binds when picked up<!--ebstats--><!--egstats--><!--eistats--><div class=\"wowhead-tooltip-item-classes\">Classes: <a href=\"/class=2\" class=\"c2\">Paladin</a></div></td></tr></table><table><tr><td>Requires Level <!--rlvl-->60<br><span class=\"q2\">Use: <a href=\"/spell=24160\" class=\"q2\">Permanently adds 10 Stamina, 7 Defense, and increases healing by up to 24 to a leg or head slot item. Does not stack with other enchantments for the selected equipment slot.</a></span></td></tr></table>",
  "url": "/item=19783/syncretists-sigil",
  "image": "https://wow.zamimg.com/images/wow/icons/medium/spell_holy_prayerofhealing.jpg",
  "id": "19783",
  "slug": "syncretists-sigil"
}