{
  "name": "Scroll: Create Signet of Beckoning",
  "quality": "Common",
  "icon": "inv_scroll_01",
  "tooltip": "<table><tr><td><!--nstart--><b class=\"q1\">Scroll: Create Signet of Beckoning</b><!--nend--><!--ndstart--><!--ndend--><span class=\"q whtt-extra whtt-ilvl\"><br>Item Level <!--ilvl-->1</span><!--bo--><!--ebstats--><!--egstats--><!--eistats--></td></tr></table><table><tr><td><span class=\"q2\">Use: <a href=\"/spell=24892\" class=\"q2\">Combine with 1 Dark Rune and 5 Enchanted Waters to create a Signet of Beckoning:Water.</a></span><div class=\"whtt-extra whtt-maxstack\">Max Stack: 20</div><div class=\"whtt-sellprice\">Sell Price: <span class=\"moneysilver\">7</span> <span class=\"moneycopper\">50</span></div></td></tr></table>",
  "url": "/item=20535/scroll-create-signet-of-beckoning",
  "image": "https://wow.zamimg.com/images/wow/icons/medium/inv_scroll_01.jpg",
  "id": "20535",
  "slug": "scroll-create-signet-of-beckoning"
}