{
  "name": "Large White Rocket",
  "quality": "Common",
  "icon": "inv_misc_missilelarge_white",
  "tooltip": "<table><tr><td><!--nstart--><b class=\"q1\">Large White Rocket</b><!--nend--><!--ndstart--><!--ndend--><span class=\"q whtt-extra whtt-ilvl\"><br>Item Level <!--ilvl-->1</span><!--bo--><!--ebstats--><!--egstats--><!--eistats--></td></tr></table><table><tr><td><span class=\"q2\">Use: <a href=\"/spell=26337\" class=\"q2\">Throw into a firework launcher!</a></span><div class=\"whtt-extra whtt-maxstack\">Max Stack: 20</div><div class=\"whtt-sellprice\">Sell Price: <span class=\"moneycopper\">12</span></div></td></tr></table>",
  "url": "/item=21593/large-white-rocket",
  "image": "https://wow.zamimg.com/images/wow/icons/medium/inv_misc_missilelarge_white.jpg",
  "id": "21593",
  "slug": "large-white-rocket"
}