{
  "name": "Cluster Rocket Recipes",
  "quality": "Common",
  "icon": "inv_scroll_05",
  "tooltip": "<table><tr><td><!--nstart--><b class=\"q1\">Cluster Rocket Recipes</b><!--nend--><!--ndstart--><!--ndend--><span class=\"q whtt-extra whtt-ilvl\"><br>Item Level <!--ilvl-->1</span><!--bo--><br />Binds when picked up<!--ebstats--><!--egstats--><!--eistats--></td></tr></table><table><tr><td><span class=\"q2\">&lt;Right Click to Open&gt;</span></td></tr></table>",
  "url": "/item=21741/cluster-rocket-recipes",
  "image": "https://wow.zamimg.com/images/wow/icons/medium/inv_scroll_05.jpg",
  "id": "21741",
  "slug": "cluster-rocket-recipes"
}