{
  "name": "Shattered Necklace",
  "quality": "Uncommon",
  "icon": "inv_jewelry_necklace_02",
  "tooltip": "<table><tr><td><!--nstart--><b class=\"q2\">Shattered Necklace</b><!--nend--><!--ndstart--><!--ndend--><span class=\"q whtt-extra whtt-ilvl\"><br>Item Level <!--ilvl-->37</span><!--bo--><br />Binds when picked up<br />Unique<br /><a href=\"/quest=2198\" class=\"q1\">This Item Begins a Quest</a><!--ebstats--><!--egstats--><!--eistats--></td></tr></table><table><tr><td>Requires Level <!--rlvl-->37</td></tr></table>",
  "url": "/item=7666/shattered-necklace",
  "image": "https://wow.zamimg.com/images/wow/icons/medium/inv_jewelry_necklace_02.jpg",
  "id": "7666",
  "slug": "shattered-necklace"
}