{
  "name": "Gahz'rilla's Electrified Scale",
  "quality": "Common",
  "icon": "inv_misc_monsterscales_03",
  "tooltip": "<table><tr><td><!--nstart--><b class=\"q1\">Gahz'rilla's Electrified Scale</b><!--nend--><!--ndstart--><!--ndend--><span class=\"q whtt-extra whtt-ilvl\"><br>Item Level <!--ilvl-->1</span><!--bo--><br />Quest Item<!--ebstats--><!--egstats--><!--eistats--></td></tr></table><table><tr><td><div class=\"whtt-extra whtt-droppedby\">Dropped by: Gahz'rilla</div><div class=\"whtt-extra whtt-dropchance\">Drop Chance: 51.95%</div></td></tr></table>",
  "url": "/item=8707/gahzrillas-electrified-scale",
  "image": "https://wow.zamimg.com/images/wow/icons/medium/inv_misc_monsterscales_03.jpg",
  "id": "8707",
  "slug": "gahzrillas-electrified-scale"
}