{
  "name": "Royal Cape",
  "quality": "Uncommon",
  "icon": "inv_misc_cape_02",
  "tooltip": "<table><tr><td><!--nstart--><b class=\"q2\">Royal Cape</b><!--nend--><!--ndstart--><!--ndend--><span class=\"q\"><br>Item Level <!--ilvl-->43</span><!--bo--><br />Binds when equipped<table width=\"100%\"><tr><td>Back</td></table><span><!--amr-->28 Armor</span><br><!--re--><span class=\"q2\">&lt;Random enchantment&gt;</span><!--ebstats--><!--egstats--><!--eistats--><!--e--><!--ps--></td></tr></table><table><tr><td>Requires Level <!--rlvl-->38<!--itemEffects:1--><div class=\"whtt-sellprice\">Sell Price: <span class=\"moneysilver\">42</span> <span class=\"moneycopper\">57</span></div></td></tr></table>",
  "url": "/item=9908/royal-cape",
  "image": "https://wow.zamimg.com/images/wow/icons/medium/inv_misc_cape_02.jpg",
  "id": "9908",
  "slug": "royal-cape"
}